fpdf/__init__.py
fpdf/actions.py
fpdf/annotations.py
fpdf/bidi.py
fpdf/deprecation.py
fpdf/drawing.py
fpdf/drawing_primitives.py
fpdf/encryption.py
fpdf/enums.py
fpdf/errors.py
fpdf/font_type_3.py
fpdf/fonts.py
fpdf/fpdf.py
fpdf/graphics_state.py
fpdf/html.py
fpdf/image_datastructures.py
fpdf/image_parsing.py
fpdf/line_break.py
fpdf/linearization.py
fpdf/outline.py
fpdf/output.py
fpdf/pattern.py
fpdf/prefs.py
fpdf/recorder.py
fpdf/sign.py
fpdf/structure_tree.py
fpdf/svg.py
fpdf/syntax.py
fpdf/table.py
fpdf/template.py
fpdf/text_region.py
fpdf/transitions.py
fpdf/unicode_script.py
fpdf/util.py
fpdf/data/__init__.py
fpdf/data/color_profiles/__init__.py
fpdf/data/color_profiles/sRGB2014.icc
fpdf/data/color_profiles/sRGB2014.icc.LICENSE
reportbro_fpdf2-2.8.2.dist-info/licenses/LICENSE
reportbro_fpdf2-2.8.2.dist-info/METADATA
reportbro_fpdf2-2.8.2.dist-info/WHEEL
reportbro_fpdf2-2.8.2.dist-info/entry_points.txt
reportbro_fpdf2-2.8.2.dist-info/top_level.txt
reportbro_fpdf2-2.8.2.dist-info/RECORD
