Metadata-Version: 2.4
Name: reportbro-fpdf2
Version: 2.8.2
Summary: Simple & fast PDF generation for Python
Author: Olivier PLATHEY, Max, Lucas Cimon (@Lucas-C),  Anderson Herzogenrath da Costa (@andersonhc)
Maintainer-email: Alex Hartmann <alex@reportbro.com>
License-Expression: LGPL-3.0-only
Project-URL: Homepage, https://www.reportbro.com
Project-URL: Documentation, https://py-pdf.github.io/fpdf2/
Project-URL: Code, https://github.com/jobsta/fpdf2
Keywords: pdf,unicode,png,jpg,ttf,barcode,library,markdown
Classifier: Development Status :: 5 - Production/Stable
Classifier: Intended Audience :: Developers
Classifier: Programming Language :: Python
Classifier: Programming Language :: Python :: 3.10
Classifier: Programming Language :: Python :: 3.11
Classifier: Programming Language :: Python :: 3.12
Classifier: Programming Language :: Python :: 3.13
Classifier: Programming Language :: Python :: 3.14
Classifier: Operating System :: OS Independent
Classifier: Topic :: Printing
Classifier: Topic :: Software Development :: Libraries :: Python Modules
Classifier: Topic :: Text Processing :: Markup
Classifier: Topic :: Multimedia :: Graphics
Classifier: Topic :: Multimedia :: Graphics :: Presentation
Requires-Python: >=3.10
License-File: LICENSE
Requires-Dist: defusedxml
Requires-Dist: Pillow!=9.2.*,>=8.3.2
Requires-Dist: fonttools>=4.34.0
Dynamic: license-file
